oandapy/__init__.py
oandapy/exceptions.py
oandapy/factories.py
oandapy/oanda.py
oandapy/validators.py
oandapy/version.py
oandapy/api/__init__.py
oandapy/api/account.py
oandapy/api/base.py
oandapy/api/instruments.py
oandapy/api/orders.py
oandapy/api/positions.py
oandapy/api/pricing.py
oandapy/api/trades.py
oandapy/api/transactions.py
oandapy-0.0.9.dist-info/LICENCE
oandapy-0.0.9.dist-info/METADATA
oandapy-0.0.9.dist-info/WHEEL
oandapy-0.0.9.dist-info/top_level.txt
oandapy-0.0.9.dist-info/RECORD
