Metadata-Version: 1.1
Name: oandapy
Version: 0.0.9
Summary: This library currently implements the features released under version 3.0.1 of OANDA's REST API.
Home-page: https://github.com/rhenter/oandapy
Author: Rafael Henter, Gustavo Ferreira
Author-email: rafael@henter.com.br
License: MIT
Keywords: translate translation command line
Platform: UNKNOWN
Classifier: Development Status :: 2 - Pre-Alpha
Classifier: Intended Audience :: End Users/Desktop
Classifier: Intended Audience :: Financial and Insurance Industry
Classifier: License :: OSI Approved :: MIT License
Classifier: Operating System :: OS Independent
Classifier: Programming Language :: Python :: 3.4
Classifier: Programming Language :: Python :: 3.5
Classifier: Programming Language :: Python :: 3.6
Classifier: Programming Language :: Python :: 3.7
Classifier: Programming Language :: Python
Classifier: Topic :: Office/Business :: Financial :: Investment
